hydrolib/__init__.py
hydrolib/arcadis/docs/index.md
hydrolib/arcadis/mkdocs.yml
hydrolib/case_management_tools/docs/index.md
hydrolib/case_management_tools/mkdocs.yml
hydrolib/dhydamo/__init__.py
hydrolib/dhydamo/converters/__init__.py
hydrolib/dhydamo/converters/df2hydrolibmodel.py
hydrolib/dhydamo/converters/hydamo2df.py
hydrolib/dhydamo/core/__init__.py
hydrolib/dhydamo/core/drr.py
hydrolib/dhydamo/core/drtc.py
hydrolib/dhydamo/core/hydamo.py
hydrolib/dhydamo/docs/developments/developments.md
hydrolib/dhydamo/docs/getting_started/index.md
hydrolib/dhydamo/docs/getting_started/installation_guide.md
hydrolib/dhydamo/docs/getting_started/output_11_0.png
hydrolib/dhydamo/docs/getting_started/output_37_1.png
hydrolib/dhydamo/docs/getting_started/output_55_0.png
hydrolib/dhydamo/docs/getting_started/output_94_0.png
hydrolib/dhydamo/docs/getting_started/tutorial.md
hydrolib/dhydamo/docs/index.md
hydrolib/dhydamo/docs/reference/api.md
hydrolib/dhydamo/geometry/__init__.py
hydrolib/dhydamo/geometry/common.py
hydrolib/dhydamo/geometry/gridgeom/checks.py
hydrolib/dhydamo/geometry/gridgeom/cstructures.py
hydrolib/dhydamo/geometry/gridgeom/geometry.py
hydrolib/dhydamo/geometry/gridgeom/gridio.py
hydrolib/dhydamo/geometry/gridgeom/links1d2d.py
hydrolib/dhydamo/geometry/gridgeom/logging.py
hydrolib/dhydamo/geometry/gridgeom/UgridReader.py
hydrolib/dhydamo/geometry/gridgeom/UgridWriter.py
hydrolib/dhydamo/geometry/mesh.py
hydrolib/dhydamo/geometry/mesh2d_gridgeom.py
hydrolib/dhydamo/geometry/models.py
hydrolib/dhydamo/geometry/rasterstats.py
hydrolib/dhydamo/geometry/spatial.py
hydrolib/dhydamo/geometry/viz.py
hydrolib/dhydamo/io/__init__.py
hydrolib/dhydamo/io/common.py
hydrolib/dhydamo/io/dimrwriter.py
hydrolib/dhydamo/io/drrreader.py
hydrolib/dhydamo/io/drrwriter.py
hydrolib/dhydamo/io/idfreader.py
hydrolib/dhydamo/mkdocs.yml
hydrolib/dhydamo/modeldata/__init__.py
hydrolib/dhydamo/resources/lib/gridgeom/gridgeom.dll
hydrolib/dhydamo/resources/RR/3b_rout.3b
hydrolib-0.4.1.dist-info/LICENSE
hydrolib-0.4.1.dist-info/METADATA
hydrolib-0.4.1.dist-info/WHEEL
hydrolib-0.4.1.dist-info/RECORD
